pygpe/__init__.py
pygpe/scalar/__init__.py
pygpe/scalar/data_manager.py
pygpe/scalar/evolution.py
pygpe/scalar/wavefunction.py
pygpe/shared/__init__.py
pygpe/shared/data_manager.py
pygpe/shared/data_manager_paths.py
pygpe/shared/grid.py
pygpe/shared/utils.py
pygpe/shared/vortices.py
pygpe/shared/wavefunction.py
pygpe/spinhalf/__init__.py
pygpe/spinhalf/data_manager.py
pygpe/spinhalf/evolution.py
pygpe/spinhalf/wavefunction.py
pygpe/spinone/__init__.py
pygpe/spinone/data_manager.py
pygpe/spinone/evolution.py
pygpe/spinone/wavefunction.py
pygpe/spintwo/__init__.py
pygpe/spintwo/data_manager.py
pygpe/spintwo/evolution.py
pygpe/spintwo/wavefunction.py
pygpe-2.0.4.dist-info/LICENSE
pygpe-2.0.4.dist-info/METADATA
pygpe-2.0.4.dist-info/WHEEL
pygpe-2.0.4.dist-info/RECORD
