Metadata-Version: 2.1
Name: pygpe
Version: 2.0.4
Summary: A fast Gross-Pitaevskii equation solver for scalar, spin-1 and spin-2 BEC systems.
Home-page: https://github.com/wheelerMT/pygpe
License: MIT
Keywords: Gross-Pitaevskii,Bose-Einstein,scientific computing,numerical methods
Author: Matt Wheeler
Author-email: wheelermt@proton.me
Requires-Python: >=3.10,<4.0
Classifier: License :: OSI Approved :: MIT License
Classifier: Programming Language :: Python :: 3
Classifier: Programming Language :: Python :: 3.10
Classifier: Programming Language :: Python :: 3.11
Classifier: Programming Language :: Python :: 3.12
Classifier: Programming Language :: Python :: 3.13
Provides-Extra: gpu
Requires-Dist: h5py (>=3.10.0,<4.0.0)
Requires-Dist: matplotlib (>=3.8.2,<4.0.0)
Requires-Dist: numpy (>=2.0.0,<3.0.0)
Project-URL: Documentation, https://wheelermt.github.io/pygpe-docs/
